praveen_weather_sdk/__init__.py
praveen_weather_sdk/client.py
praveen_weather_sdk-1.0.0.dist-info/METADATA
praveen_weather_sdk-1.0.0.dist-info/WHEEL
praveen_weather_sdk-1.0.0.dist-info/top_level.txt
praveen_weather_sdk-1.0.0.dist-info/RECORD
