Metadata-Version: 2.4
Name: praveen_weather_sdk
Version: 1.0.0
Summary: A simple Python SDK for fetching weather data
Author: Praveen Kumar Bharti
Author-email: praveen.theguru2020@gmail.com
License: None
Requires-Python: >=3.6
Requires-Dist: requests>=2.20
Dynamic: author
Dynamic: author-email
Dynamic: license
Dynamic: requires-dist
Dynamic: requires-python
Dynamic: summary
